modular_ml_agents/__init__.py
modular_ml_agents/custom_ppo_plugin/__init__.py
modular_ml_agents/custom_ppo_plugin/action_model_aggregated.py
modular_ml_agents/custom_ppo_plugin/optimizer.py
modular_ml_agents/custom_ppo_plugin/trainer.py
modular_ml_agents/custom_ppo_plugin/wrapper_actor.py
modular_ml_agents/custom_ppo_plugin/layers/__init__.py
modular_ml_agents/custom_ppo_plugin/layers/brain_mlp.py
modular_ml_agents-1.0.0.dist-info/LICENSE
modular_ml_agents-1.0.0.dist-info/METADATA
modular_ml_agents-1.0.0.dist-info/WHEEL
modular_ml_agents-1.0.0.dist-info/entry_points.txt
modular_ml_agents-1.0.0.dist-info/top_level.txt
modular_ml_agents-1.0.0.dist-info/RECORD
