Metadata-Version: 2.2
Name: modular_ml_agents
Version: 1.0.0
Summary: Unity ML-Agents plugin used by https://github.com/Alexiush/ML-Agents-Modular
Author-email: Alexiush <streltsov2609@gmail.com>
License: MIT License
Project-URL: Homepage, https://github.com/Alexiush/modular-ml-agents
Project-URL: Issues, https://github.com/Alexiush/modular-ml-agents/issues
Classifier: Programming Language :: Python :: 3
Classifier: Operating System :: OS Independent
Requires-Python: >=3.10.1
License-File: LICENSE
Requires-Dist: mlagents>=1.1.0
Requires-Dist: mlagents_envs>=1.1.0
